jupyterlab_terminal_show_in_file_browser_extension/__init__.py
jupyterlab_terminal_show_in_file_browser_extension/_version.py
jupyterlab_terminal_show_in_file_browser_extension/handlers.py
jupyterlab_terminal_show_in_file_browser_extension/tests/__init__.py
jupyterlab_terminal_show_in_file_browser_extension/tests/test_handlers.py
jupyterlab_terminal_show_in_file_browser_extension-1.0.20.data/data/etc/jupyter/jupyter_server_config.d/jupyterlab_terminal_show_in_file_browser_extension.json
jupyterlab_terminal_show_in_file_browser_extension-1.0.20.data/data/share/jupyter/labextensions/jupyterlab_terminal_show_in_file_browser_extension/package.json
jupyterlab_terminal_show_in_file_browser_extension-1.0.20.data/data/share/jupyter/labextensions/jupyterlab_terminal_show_in_file_browser_extension/schemas/jupyterlab_terminal_show_in_file_browser_extension/package.json.orig
jupyterlab_terminal_show_in_file_browser_extension-1.0.20.data/data/share/jupyter/labextensions/jupyterlab_terminal_show_in_file_browser_extension/schemas/jupyterlab_terminal_show_in_file_browser_extension/plugin.json
jupyterlab_terminal_show_in_file_browser_extension-1.0.20.data/data/share/jupyter/labextensions/jupyterlab_terminal_show_in_file_browser_extension/static/509.2d3a1c0521c1004b487b.js
jupyterlab_terminal_show_in_file_browser_extension-1.0.20.data/data/share/jupyter/labextensions/jupyterlab_terminal_show_in_file_browser_extension/static/728.fe213ec6882091e4935b.js
jupyterlab_terminal_show_in_file_browser_extension-1.0.20.data/data/share/jupyter/labextensions/jupyterlab_terminal_show_in_file_browser_extension/static/remoteEntry.954850a9511644e2a4be.js
jupyterlab_terminal_show_in_file_browser_extension-1.0.20.data/data/share/jupyter/labextensions/jupyterlab_terminal_show_in_file_browser_extension/static/style.js
jupyterlab_terminal_show_in_file_browser_extension-1.0.20.data/data/share/jupyter/labextensions/jupyterlab_terminal_show_in_file_browser_extension/static/third-party-licenses.json
jupyterlab_terminal_show_in_file_browser_extension-1.0.20.dist-info/METADATA
jupyterlab_terminal_show_in_file_browser_extension-1.0.20.dist-info/WHEEL
jupyterlab_terminal_show_in_file_browser_extension-1.0.20.dist-info/licenses/LICENSE
jupyterlab_terminal_show_in_file_browser_extension-1.0.20.dist-info/RECORD
