Metadata-Version: 2.4
Name: jupyterlab_terminal_show_in_file_browser_extension
Version: 1.0.20
Summary: Jupyterlab extension to add context menu item to the terminal tab to navigate file browser to the pwd path of the terminal
Project-URL: Homepage, https://github.com/stellarshenson/jupyterlab_terminal_show_in_file_browser_extension
Project-URL: Bug Tracker, https://github.com/stellarshenson/jupyterlab_terminal_show_in_file_browser_extension/issues
Project-URL: Repository, https://github.com/stellarshenson/jupyterlab_terminal_show_in_file_browser_extension.git
Author-email: Stellars Henson <konrad.jelen@gmail.com>
License: BSD 3-Clause License
License-File: LICENSE
Keywords: jupyter,jupyterlab,jupyterlab-extension
Classifier: Framework :: Jupyter
Classifier: Framework :: Jupyter :: JupyterLab
Classifier: Framework :: Jupyter :: JupyterLab :: 4
Classifier: Framework :: Jupyter :: JupyterLab :: Extensions
Classifier: Framework :: Jupyter :: JupyterLab :: Extensions :: Prebuilt
Classifier: License :: OSI Approved :: BSD License
Classifier: Programming Language :: Python
Classifier: Programming Language :: Python :: 3
Classifier: Programming Language :: Python :: 3.9
Classifier: Programming Language :: Python :: 3.10
Classifier: Programming Language :: Python :: 3.11
Classifier: Programming Language :: Python :: 3.12
Classifier: Programming Language :: Python :: 3.13
Requires-Python: >=3.9
Provides-Extra: test
Requires-Dist: pytest-cov; extra == 'test'
Requires-Dist: pytest>=7.0; extra == 'test'
